ffmphisdp/__init__.py
ffmphisdp/pyav_reader.py
ffmphisdp/utils.py
ffmphisdp/video_reader.py
ffmphisdp-2.6.2.dist-info/METADATA
ffmphisdp-2.6.2.dist-info/WHEEL
ffmphisdp-2.6.2.dist-info/RECORD
