Metadata-Version: 2.4
Name: ffmphisdp
Version: 2.6.2
Author-email: Jimmy Huguet <jimmy.huguet@skillcorner.com>
Requires-Python: <3.14,>=3.9
Requires-Dist: av<15,>=12
Requires-Dist: ffmpeg-python>=0.2.0
Requires-Dist: numpy<2,>=1.18.5; python_version < '3.12'
Requires-Dist: numpy>=1.26.4; python_version ~= '3.12'
Requires-Dist: numpy>=2; python_version >= '3.13'
Requires-Dist: tqdm>=4.66.4
Requires-External: pkg:generic/ffmpeg
